setup.py
mongoengine_fuel/__init__.py
mongoengine_fuel/fuel.py
mongoengine_fuel/generators.py
mongoengine_fuel.egg-info/PKG-INFO
mongoengine_fuel.egg-info/SOURCES.txt
mongoengine_fuel.egg-info/dependency_links.txt
mongoengine_fuel.egg-info/top_level.txt