Metadata-Version: 1.0
Name: mongoengine-fuel
Version: 1.0.2
Summary: Factory for MongoDB documents created with mongoengine
Home-page: http://github.com/berinhard/mongoengine_fuel
Author: Bernardo Fontes
Author-email: falecomigo@bernardofontes.net
License: http://www.gnu.org/licenses/lgpl.html
Keywords: factory documents mongodb mongoengine
Platform: UNKNOWN
